{
  "analysis": {
    "analyzer": {
      "nori_analyzer": {
        "type": "custom",
        "tokenizer": "nori_tokenizer",
        "filter": ["lowercase"]
      },
      "edge_ngram_analyzer": {
        "type": "custom",
        "tokenizer": "edge_ngram_tokenizer",
        "filter": ["lowercase"]
      },
      "nori_synonym_analyzer": {
        "type": "custom",
        "tokenizer": "nori_tokenizer",
        "filter": ["lowercase", "synonym_filter"]
      }
    },
    "tokenizer": {
      "nori_tokenizer": {
        "type": "nori_tokenizer",
        "decompound_mode": "mixed"
      },
      "edge_ngram_tokenizer": {
        "type": "edge_ngram",
        "min_gram": 1,
        "max_gram": 20,
        "token_chars": ["letter", "digit"]
      }
    },
    "filter": {
      "synonym_filter": {
        "type": "synonym_graph",
        "synonyms": [
          "삼성,샘숭,삼송,samsung",
          "lg,엘지,앨지,엘쥐,앨쥐",
          "바지, 팬츠, pants, 슬랙스, 조거팬츠, 레깅스, 하의"
        ],
        "lenient": true
      }
    },
    "normalizer": {
      "lowercase_normalizer": {
        "type": "custom",
        "filter": ["lowercase"]
      }
    }
  }
}

